README.md
pyproject.toml
setup.py
kivar/__init__.py
kivar/kivar_cli.py
kivar/kivar_engine.py
kivar/kivar_version.py
kivar.egg-info/PKG-INFO
kivar.egg-info/SOURCES.txt
kivar.egg-info/dependency_links.txt
kivar.egg-info/entry_points.txt
kivar.egg-info/top_level.txt