Metadata-Version: 2.1
Name: kivar
Version: 0.5.0
Summary: PCB Assembly Variants for KiCad
Home-page: https://github.com/markh-de/KiVar
Author: Mark Hämmerling
Author-email: dev@markh.de
License: MIT
